certbot_dns_beget/__init__.py
certbot_dns_beget/_internal/__init__.py
certbot_dns_beget/_internal/dns_beget.py
certbot_dns_beget-1.7.0.dev3.dist-info/LICENSE.txt
certbot_dns_beget-1.7.0.dev3.dist-info/METADATA
certbot_dns_beget-1.7.0.dev3.dist-info/WHEEL
certbot_dns_beget-1.7.0.dev3.dist-info/entry_points.txt
certbot_dns_beget-1.7.0.dev3.dist-info/top_level.txt
certbot_dns_beget-1.7.0.dev3.dist-info/RECORD
