Metadata-Version: 2.1
Name: certbot-dns-beget
Version: 1.7.0.dev3
Summary: Beget DNS Authenticator plugin for Certbot
Home-page: https://github.com/skrashevich/certbot-dns-beget
Author: Certbot Project
Author-email: s.krashevich@gmail.com
License: Apache License 2.0
Platform: UNKNOWN
Classifier: Development Status :: 5 - Production/Stable
Classifier: Environment :: Plugins
Classifier: Intended Audience :: System Administrators
Classifier: License :: OSI Approved :: Apache Software License
Classifier: Operating System :: POSIX :: Linux
Classifier: Programming Language :: Python
Classifier: Programming Language :: Python :: 3
Classifier: Programming Language :: Python :: 3.5
Classifier: Programming Language :: Python :: 3.6
Classifier: Programming Language :: Python :: 3.7
Classifier: Programming Language :: Python :: 3.8
Classifier: Topic :: Internet :: WWW/HTTP
Classifier: Topic :: Security
Classifier: Topic :: System :: Installation/Setup
Classifier: Topic :: System :: Networking
Classifier: Topic :: System :: Systems Administration
Classifier: Topic :: Utilities
Requires-Python: >=3.7
Requires-Dist: requests
Requires-Dist: setuptools
Requires-Dist: zope.interface
Requires-Dist: acme >=1.7.0.dev3
Requires-Dist: certbot >=1.7.0.dev3
Requires-Dist: mock ; python_version < "3.3"
Provides-Extra: docs
Requires-Dist: Sphinx >=1.0 ; extra == 'docs'
Requires-Dist: sphinx-rtd-theme ; extra == 'docs'
